flake8_print.py
flake8_print_clean-3.1.4.dist-info/LICENCE
flake8_print_clean-3.1.4.dist-info/METADATA
flake8_print_clean-3.1.4.dist-info/WHEEL
flake8_print_clean-3.1.4.dist-info/entry_points.txt
flake8_print_clean-3.1.4.dist-info/top_level.txt
flake8_print_clean-3.1.4.dist-info/RECORD
