Metadata-Version: 2.1
Name: flake8-print-clean
Version: 3.1.4
Summary: print statement checker plugin for flake8
Home-page: https://github.com/jbkahn/flake8-print
Author: Joseph Kahn
Author-email: josephbkahn@gmail.com
License: MIT
Keywords: flake8 print
Platform: UNKNOWN
Classifier: Development Status :: 3 - Alpha
Classifier: Environment :: Console
Classifier: Framework :: Flake8
Classifier: Intended Audience :: Developers
Classifier: License :: OSI Approved :: MIT License
Classifier: Operating System :: OS Independent
Classifier: Programming Language :: Python
Classifier: Programming Language :: Python :: 2
Classifier: Programming Language :: Python :: 3
Classifier: Topic :: Software Development :: Libraries :: Python Modules
Classifier: Topic :: Software Development :: Quality Assurance
Requires-Dist: flake8 (>=1.5)
Requires-Dist: six
Requires-Dist: pycodestyle
